<CAMEO_XML>

  <Document id="AFP_ENG_20090401.0806">
    <Sentences>
      <Sentence char_offsets="202:382" id="0" />
      <Sentence char_offsets="393:622" id="1" />
      <Sentence char_offsets="633:854" id="2" />
      <Sentence char_offsets="865:1086" id="3" />
      <Sentence char_offsets="1097:1172" id="4" />
      <Sentence char_offsets="1183:1329" id="5" />
      <Sentence char_offsets="1340:1486" id="6" />
      <Sentence char_offsets="1497:1598" id="7" />
      <Sentence char_offsets="1609:1799" id="8" />
      <Sentence char_offsets="1810:1946" id="9" />
      <Sentence char_offsets="1957:2182" id="10" />
      <Sentence char_offsets="2193:2386" id="11" />
      <Sentence char_offsets="2397:2590" id="12" />
      <Sentence char_offsets="2601:2772" id="13" />
      <Sentence char_offsets="2783:3014" id="14" />
    </Sentences>
    <Events />
  </Document>

</CAMEO_XML>