<CAMEO_XML>

  <Document id="AFP_ENG_20090302.0053">
    <Sentences>
      <Sentence char_offsets="193:380" id="0" />
      <Sentence char_offsets="391:608" id="1" />
      <Sentence char_offsets="619:825" id="2" />
      <Sentence char_offsets="836:941" id="3" />
      <Sentence char_offsets="952:1148" id="4" />
      <Sentence char_offsets="1159:1407" id="5" />
      <Sentence char_offsets="1418:1585" id="6" />
      <Sentence char_offsets="1596:1744" id="7" />
      <Sentence char_offsets="1755:1858" id="8" />
      <Sentence char_offsets="1860:1992" id="9" />
      <Sentence char_offsets="2003:2173" id="10" />
      <Sentence char_offsets="2184:2394" id="11" />
      <Sentence char_offsets="2405:2570" id="12" />
      <Sentence char_offsets="2572:2702" id="13" />
      <Sentence char_offsets="2713:2874" id="14" />
      <Sentence char_offsets="2885:3051" id="15" />
      <Sentence char_offsets="3053:3137" id="16" />
      <Sentence char_offsets="3148:3266" id="17" />
      <Sentence char_offsets="3277:3553" id="18" />
      <Sentence char_offsets="3564:3766" id="19" />
      <Sentence char_offsets="3777:3958" id="20" />
      <Sentence char_offsets="3969:4065" id="21" />
      <Sentence char_offsets="4076:4202" id="22" />
      <Sentence char_offsets="4213:4425" id="23" />
      <Sentence char_offsets="4436:4504" id="24" />
      <Sentence char_offsets="4515:4767" id="25" />
    </Sentences>
    <Events />
  </Document>

</CAMEO_XML>