<CAMEO_XML>

  <Document id="APW_ENG_20090310.0476">
    <Sentences>
      <Sentence char_offsets="169:310" id="0" />
      <Sentence char_offsets="321:538" id="1" />
      <Sentence char_offsets="540:615" id="2" />
      <Sentence char_offsets="626:716" id="3" />
      <Sentence char_offsets="727:866" id="4" />
      <Sentence char_offsets="877:1050" id="5" />
      <Sentence char_offsets="1061:1221" id="6" />
      <Sentence char_offsets="1223:1378" id="7" />
      <Sentence char_offsets="1389:1504" id="8" />
      <Sentence char_offsets="1506:1570" id="9" />
      <Sentence char_offsets="1581:1701" id="10" />
      <Sentence char_offsets="1703:1758" id="11" />
      <Sentence char_offsets="1769:1912" id="12" />
      <Sentence char_offsets="1914:1997" id="13" />
      <Sentence char_offsets="2008:2061" id="14" />
      <Sentence char_offsets="2072:2284" id="15" />
      <Sentence char_offsets="2295:2411" id="16" />
      <Sentence char_offsets="2413:2471" id="17" />
      <Sentence char_offsets="2482:2609" id="18" />
      <Sentence char_offsets="2620:2625" id="19" />
      <Sentence char_offsets="2636:2646" id="20" />
      <Sentence char_offsets="2657:2674" id="21" />
    </Sentences>
    <Events />
  </Document>

</CAMEO_XML>