<CAMEO_XML>

  <Document id="APW_ENG_20090326.0311">
    <Sentences>
      <Sentence char_offsets="190:409" id="0" />
      <Sentence char_offsets="420:536" id="1" />
      <Sentence char_offsets="547:609" id="2" />
      <Sentence char_offsets="611:696" id="3" />
      <Sentence char_offsets="707:852" id="4" />
      <Sentence char_offsets="863:1100" id="5" />
      <Sentence char_offsets="1111:1192" id="6" />
      <Sentence char_offsets="1194:1224" id="7" />
      <Sentence char_offsets="1226:1250" id="8" />
      <Sentence char_offsets="1261:1387" id="9" />
      <Sentence char_offsets="1389:1470" id="10" />
      <Sentence char_offsets="1481:1573" id="11" />
      <Sentence char_offsets="1575:1647" id="12" />
      <Sentence char_offsets="1649:1764" id="13" />
      <Sentence char_offsets="1775:1970" id="14" />
      <Sentence char_offsets="1972:2123" id="15" />
      <Sentence char_offsets="2134:2224" id="16" />
      <Sentence char_offsets="2226:2324" id="17" />
      <Sentence char_offsets="2335:2425" id="18" />
      <Sentence char_offsets="2427:2479" id="19" />
      <Sentence char_offsets="2490:2556" id="20" />
      <Sentence char_offsets="2558:2616" id="21" />
      <Sentence char_offsets="2627:2679" id="22" />
      <Sentence char_offsets="2681:2750" id="23" />
      <Sentence char_offsets="2752:2790" id="24" />
      <Sentence char_offsets="2801:2895" id="25" />
      <Sentence char_offsets="2897:3029" id="26" />
      <Sentence char_offsets="3031:3174" id="27" />
      <Sentence char_offsets="3185:3309" id="28" />
      <Sentence char_offsets="3320:3362" id="29" />
      <Sentence char_offsets="3364:3386" id="30" />
    </Sentences>
    <Events />
  </Document>

</CAMEO_XML>