<CAMEO_XML>

  <Document id="APW_ENG_20090403.1461">
    <Sentences>
      <Sentence char_offsets="187:359" id="0" />
      <Sentence char_offsets="370:485" id="1" />
      <Sentence char_offsets="496:676" id="2" />
      <Sentence char_offsets="687:743" id="3" />
      <Sentence char_offsets="754:864" id="4" />
      <Sentence char_offsets="866:948" id="5" />
      <Sentence char_offsets="959:1147" id="6" />
      <Sentence char_offsets="1158:1244" id="7" />
      <Sentence char_offsets="1246:1281" id="8" />
      <Sentence char_offsets="1292:1534" id="9" />
      <Sentence char_offsets="1545:1725" id="10" />
      <Sentence char_offsets="1727:1824" id="11" />
      <Sentence char_offsets="1835:1987" id="12" />
      <Sentence char_offsets="1998:2171" id="13" />
      <Sentence char_offsets="2173:2295" id="14" />
      <Sentence char_offsets="2306:2502" id="15" />
      <Sentence char_offsets="2513:2658" id="16" />
      <Sentence char_offsets="2669:2767" id="17" />
      <Sentence char_offsets="2778:2938" id="18" />
      <Sentence char_offsets="2940:3002" id="19" />
      <Sentence char_offsets="3013:3098" id="20" />
      <Sentence char_offsets="3100:3186" id="21" />
      <Sentence char_offsets="3197:3306" id="22" />
      <Sentence char_offsets="3308:3356" id="23" />
      <Sentence char_offsets="3367:3478" id="24" />
      <Sentence char_offsets="3480:3648" id="25" />
      <Sentence char_offsets="3659:3734" id="26" />
      <Sentence char_offsets="3736:3906" id="27" />
    </Sentences>
    <Events />
  </Document>

</CAMEO_XML>