<CAMEO_XML>

  <Document id="APW_ENG_20090426.0550">
    <Sentences>
      <Sentence char_offsets="177:254" id="0" />
      <Sentence char_offsets="265:398" id="1" />
      <Sentence char_offsets="409:459" id="2" />
      <Sentence char_offsets="461:635" id="3" />
      <Sentence char_offsets="646:758" id="4" />
      <Sentence char_offsets="760:889" id="5" />
      <Sentence char_offsets="891:943" id="6" />
      <Sentence char_offsets="954:1054" id="7" />
      <Sentence char_offsets="1065:1232" id="8" />
      <Sentence char_offsets="1243:1487" id="9" />
      <Sentence char_offsets="1489:1544" id="10" />
      <Sentence char_offsets="1555:1679" id="11" />
      <Sentence char_offsets="1690:1891" id="12" />
      <Sentence char_offsets="1893:1986" id="13" />
      <Sentence char_offsets="1988:2090" id="14" />
      <Sentence char_offsets="2101:2227" id="15" />
      <Sentence char_offsets="2229:2292" id="16" />
      <Sentence char_offsets="2294:2431" id="17" />
      <Sentence char_offsets="2442:2500" id="18" />
      <Sentence char_offsets="2502:2694" id="19" />
      <Sentence char_offsets="2696:2750" id="20" />
    </Sentences>
    <Events />
  </Document>

</CAMEO_XML>