<CAMEO_XML>

  <Document id="NYT_ENG_20090308.0029">
    <Sentences>
      <Sentence char_offsets="109:149" id="0" />
      <Sentence char_offsets="151:158" id="1" />
      <Sentence char_offsets="169:462" id="2" />
      <Sentence char_offsets="473:712" id="3" />
      <Sentence char_offsets="723:828" id="4" />
      <Sentence char_offsets="830:911" id="5" />
      <Sentence char_offsets="913:1109" id="6" />
      <Sentence char_offsets="1111:1263" id="7" />
      <Sentence char_offsets="1274:1327" id="8" />
      <Sentence char_offsets="1329:1613" id="9" />
      <Sentence char_offsets="1615:1800" id="10" />
      <Sentence char_offsets="1811:2039" id="11" />
      <Sentence char_offsets="2041:2223" id="12" />
      <Sentence char_offsets="2234:2365" id="13" />
      <Sentence char_offsets="2367:2480" id="14" />
      <Sentence char_offsets="2482:2629" id="15" />
      <Sentence char_offsets="2631:2861" id="16" />
      <Sentence char_offsets="2872:2960" id="17" />
      <Sentence char_offsets="2962:3119" id="18" />
      <Sentence char_offsets="3121:3194" id="19" />
      <Sentence char_offsets="3196:3299" id="20" />
      <Sentence char_offsets="3310:3401" id="21" />
      <Sentence char_offsets="3403:3575" id="22" />
      <Sentence char_offsets="3577:3657" id="23" />
      <Sentence char_offsets="3668:3701" id="24" />
      <Sentence char_offsets="3703:3827" id="25" />
      <Sentence char_offsets="3829:3883" id="26" />
      <Sentence char_offsets="3885:3928" id="27" />
      <Sentence char_offsets="3930:4032" id="28" />
      <Sentence char_offsets="4043:4167" id="29" />
      <Sentence char_offsets="4169:4322" id="30" />
      <Sentence char_offsets="4324:4479" id="31" />
      <Sentence char_offsets="4490:4587" id="32" />
      <Sentence char_offsets="4589:4635" id="33" />
      <Sentence char_offsets="4637:4723" id="34" />
      <Sentence char_offsets="4725:4802" id="35" />
      <Sentence char_offsets="4813:4908" id="36" />
      <Sentence char_offsets="4910:5004" id="37" />
      <Sentence char_offsets="5006:5191" id="38" />
      <Sentence char_offsets="5202:5409" id="39" />
      <Sentence char_offsets="5411:5492" id="40" />
      <Sentence char_offsets="5503:5588" id="41" />
      <Sentence char_offsets="5590:5664" id="42" />
      <Sentence char_offsets="5666:5832" id="43" />
      <Sentence char_offsets="5843:5897" id="44" />
      <Sentence char_offsets="5899:6083" id="45" />
      <Sentence char_offsets="6085:6175" id="46" />
      <Sentence char_offsets="6177:6252" id="47" />
    </Sentences>
    <Events />
  </Document>

</CAMEO_XML>