<CAMEO_XML>

  <Document id="NYT_ENG_20090325.0102">
    <Sentences>
      <Sentence char_offsets="165:382" id="0" />
      <Sentence char_offsets="384:480" id="1" />
      <Sentence char_offsets="491:543" id="2" />
      <Sentence char_offsets="545:573" id="3" />
      <Sentence char_offsets="584:705" id="4" />
      <Sentence char_offsets="707:922" id="5" />
      <Sentence char_offsets="924:989" id="6" />
      <Sentence char_offsets="1000:1099" id="7" />
      <Sentence char_offsets="1101:1147" id="8" />
      <Sentence char_offsets="1158:1326" id="9" />
      <Sentence char_offsets="1337:1433" id="10" />
      <Sentence char_offsets="1435:1474" id="11" />
      <Sentence char_offsets="1476:1512" id="12" />
      <Sentence char_offsets="1523:1666" id="13" />
      <Sentence char_offsets="1668:1806" id="14" />
      <Sentence char_offsets="1808:1910" id="15" />
      <Sentence char_offsets="1921:1995" id="16" />
      <Sentence char_offsets="1997:2072" id="17" />
      <Sentence char_offsets="2074:2105" id="18" />
      <Sentence char_offsets="2116:2326" id="19" />
      <Sentence char_offsets="2337:2413" id="20" />
      <Sentence char_offsets="2415:2559" id="21" />
      <Sentence char_offsets="2570:2606" id="22" />
      <Sentence char_offsets="2608:2633" id="23" />
      <Sentence char_offsets="2635:2659" id="24" />
      <Sentence char_offsets="2670:2757" id="25" />
      <Sentence char_offsets="2759:2893" id="26" />
      <Sentence char_offsets="2895:2976" id="27" />
      <Sentence char_offsets="2987:3106" id="28" />
      <Sentence char_offsets="3108:3228" id="29" />
      <Sentence char_offsets="3239:3292" id="30" />
      <Sentence char_offsets="3294:3347" id="31" />
      <Sentence char_offsets="3358:3502" id="32" />
      <Sentence char_offsets="3504:3609" id="33" />
      <Sentence char_offsets="3620:3735" id="34" />
      <Sentence char_offsets="3737:3831" id="35" />
      <Sentence char_offsets="3833:3852" id="36" />
      <Sentence char_offsets="3863:3935" id="37" />
      <Sentence char_offsets="3937:3999" id="38" />
      <Sentence char_offsets="4010:4059" id="39" />
      <Sentence char_offsets="4061:4103" id="40" />
      <Sentence char_offsets="4105:4164" id="41" />
      <Sentence char_offsets="4166:4279" id="42" />
      <Sentence char_offsets="4281:4355" id="43" />
      <Sentence char_offsets="4357:4380" id="44" />
      <Sentence char_offsets="4391:4478" id="45" />
      <Sentence char_offsets="4489:4637" id="46" />
      <Sentence char_offsets="4639:4736" id="47" />
      <Sentence char_offsets="4747:4787" id="48" />
      <Sentence char_offsets="4789:4816" id="49" />
      <Sentence char_offsets="4827:4989" id="50" />
      <Sentence char_offsets="5000:5044" id="51" />
      <Sentence char_offsets="5046:5075" id="52" />
      <Sentence char_offsets="5077:5112" id="53" />
      <Sentence char_offsets="5123:5217" id="54" />
      <Sentence char_offsets="5219:5337" id="55" />
      <Sentence char_offsets="5339:5386" id="56" />
      <Sentence char_offsets="5388:5425" id="57" />
      <Sentence char_offsets="5436:5520" id="58" />
      <Sentence char_offsets="5522:5578" id="59" />
      <Sentence char_offsets="5589:5696" id="60" />
      <Sentence char_offsets="5698:5740" id="61" />
      <Sentence char_offsets="5751:5842" id="62" />
      <Sentence char_offsets="5844:5884" id="63" />
      <Sentence char_offsets="5895:5939" id="64" />
    </Sentences>
    <Events />
  </Document>

</CAMEO_XML>