<CAMEO_XML>

  <Document id="NYT_ENG_20090423.0237">
    <Sentences>
      <Sentence char_offsets="117:138" id="0" />
      <Sentence char_offsets="149:218" id="1" />
      <Sentence char_offsets="220:248" id="2" />
      <Sentence char_offsets="250:306" id="3" />
      <Sentence char_offsets="308:372" id="4" />
      <Sentence char_offsets="383:414" id="5" />
      <Sentence char_offsets="425:511" id="6" />
      <Sentence char_offsets="513:579" id="7" />
      <Sentence char_offsets="581:595" id="8" />
      <Sentence char_offsets="606:711" id="9" />
      <Sentence char_offsets="713:756" id="10" />
      <Sentence char_offsets="758:849" id="11" />
      <Sentence char_offsets="860:941" id="12" />
      <Sentence char_offsets="952:1213" id="13" />
      <Sentence char_offsets="1224:1253" id="14" />
      <Sentence char_offsets="1255:1291" id="15" />
      <Sentence char_offsets="1302:1350" id="16" />
      <Sentence char_offsets="1361:1451" id="17" />
      <Sentence char_offsets="1462:1577" id="18" />
      <Sentence char_offsets="1588:1769" id="19" />
      <Sentence char_offsets="1771:1822" id="20" />
      <Sentence char_offsets="1823:1826" id="21" />
      <Sentence char_offsets="1837:2001" id="22" />
      <Sentence char_offsets="2003:2098" id="23" />
      <Sentence char_offsets="2109:2217" id="24" />
      <Sentence char_offsets="2228:2315" id="25" />
      <Sentence char_offsets="2317:2464" id="26" />
      <Sentence char_offsets="2475:2590" id="27" />
      <Sentence char_offsets="2601:2682" id="28" />
      <Sentence char_offsets="2684:2768" id="29" />
      <Sentence char_offsets="2770:2917" id="30" />
      <Sentence char_offsets="2928:2983" id="31" />
      <Sentence char_offsets="2985:3063" id="32" />
      <Sentence char_offsets="3065:3125" id="33" />
      <Sentence char_offsets="3136:3169" id="34" />
      <Sentence char_offsets="3171:3198" id="35" />
      <Sentence char_offsets="3200:3258" id="36" />
      <Sentence char_offsets="3269:3402" id="37" />
      <Sentence char_offsets="3404:3488" id="38" />
      <Sentence char_offsets="3499:3578" id="39" />
      <Sentence char_offsets="3580:3629" id="40" />
      <Sentence char_offsets="3631:3744" id="41" />
      <Sentence char_offsets="3755:3808" id="42" />
      <Sentence char_offsets="3810:3936" id="43" />
      <Sentence char_offsets="3938:4024" id="44" />
      <Sentence char_offsets="4035:4109" id="45" />
      <Sentence char_offsets="4111:4211" id="46" />
      <Sentence char_offsets="4222:4259" id="47" />
      <Sentence char_offsets="4261:4341" id="48" />
      <Sentence char_offsets="4343:4379" id="49" />
      <Sentence char_offsets="4390:4401" id="50" />
      <Sentence char_offsets="4412:4459" id="51" />
    </Sentences>
    <Events />
  </Document>

</CAMEO_XML>