<CAMEO_XML>

  <Document id="NYT_ENG_20090401.0151">
    <Sentences>
      <Sentence char_offsets="120:137" id="0" />
      <Sentence char_offsets="139:391" id="1" />
      <Sentence char_offsets="402:693" id="2" />
      <Sentence char_offsets="704:867" id="3" />
      <Sentence char_offsets="869:1043" id="4" />
      <Sentence char_offsets="1045:1148" id="5" />
      <Sentence char_offsets="1159:1328" id="6" />
      <Sentence char_offsets="1339:1603" id="7" />
      <Sentence char_offsets="1614:1837" id="8" />
      <Sentence char_offsets="1848:2093" id="9" />
      <Sentence char_offsets="2095:2185" id="10" />
      <Sentence char_offsets="2196:2451" id="11" />
      <Sentence char_offsets="2462:2675" id="12" />
      <Sentence char_offsets="2686:2849" id="13" />
      <Sentence char_offsets="2851:2955" id="14" />
      <Sentence char_offsets="2966:3126" id="15" />
      <Sentence char_offsets="3137:3313" id="16" />
      <Sentence char_offsets="3315:3439" id="17" />
      <Sentence char_offsets="3441:3544" id="18" />
      <Sentence char_offsets="3555:3635" id="19" />
      <Sentence char_offsets="3646:3823" id="20" />
    </Sentences>
    <Events />
  </Document>

</CAMEO_XML>